aliad/__init__.py
aliad/_version.py
aliad/components/__init__.py
aliad/components/activations.py
aliad/components/backend_class.py
aliad/components/bootstrapping.py
aliad/components/evaluation.py
aliad/components/metrics.py
aliad/components/outputs.py
aliad/core/__init__.py
aliad/core/assertions.py
aliad/core/dtypes.py
aliad/core/mixins.py
aliad/core/sdtypes.py
aliad/core/tasktypes.py
aliad/data/__init__.py
aliad/data/formats.py
aliad/data/loader.py
aliad/data/metadata.py
aliad/data/partition.py
aliad/data/point_cloud_dataset.py
aliad/features/__init__.py
aliad/features/feature.py
aliad/features/spec.py
aliad/features/tabular.py
aliad/interface/__init__.py
aliad/interface/awkward/__init__.py
aliad/interface/awkward/momentum_4d_array_builder.py
aliad/interface/awkward/utils.py
aliad/interface/fastjet/__init__.py
aliad/interface/fastjet/jet_clustering_tool.py
aliad/interface/keras/__init__.py
aliad/interface/keras/_internals.py
aliad/interface/keras/activations.py
aliad/interface/keras/layers.py
aliad/interface/keras/ops.py
aliad/interface/keras/regularizers.py
aliad/interface/keras/utils.py
aliad/interface/tensorflow/__init__.py
aliad/interface/tensorflow/callbacks.py
aliad/interface/tensorflow/dataset.py
aliad/interface/tensorflow/layers.py
aliad/interface/tensorflow/losses.py
aliad/interface/tensorflow/operations.py
aliad/interface/tensorflow/regularizers.py
aliad/interface/tensorflow/tfrecord_maker.py
aliad/interface/tensorflow/utils.py
aliad/interface/tensorflow/models/MLP.py
aliad/interface/tensorflow/models/MultiParticleNet.py
aliad/interface/tensorflow/models/__init__.py
aliad/utils/__init__.py
aliad/utils/array_utils.py
aliad/utils/system_utils.py
aliad-0.2.1.0.data/scripts/aliad
aliad-0.2.1.0.dist-info/LICENSE
aliad-0.2.1.0.dist-info/METADATA
aliad-0.2.1.0.dist-info/WHEEL
aliad-0.2.1.0.dist-info/top_level.txt
aliad-0.2.1.0.dist-info/RECORD
