Metadata-Version: 2.1
Name: aliad
Version: 0.2.1.0
Summary: A library for anomaly detection.
Author: Alkaid Cheng
Author-email: chi.lung.cheng@cern.ch
Classifier: Programming Language :: Python
Classifier: Programming Language :: Python :: 3
Classifier: Programming Language :: Python :: 3.8
Classifier: Programming Language :: Python :: 3.9
Classifier: Programming Language :: Python :: 3.10
Classifier: License :: OSI Approved :: Apache Software License
Classifier: Operating System :: OS Independent
Requires-Python: >=3.8
License-File: LICENSE
Requires-Dist: numpy
Requires-Dist: scipy
Requires-Dist: numba
Requires-Dist: pandas
Requires-Dist: matplotlib
Requires-Dist: click
Requires-Dist: quickstats
